just/__init__.py
just/cli.py
just/commands/__init__.py
just/commands/download.py
just/commands/edit.py
just/commands/extract.py
just/commands/install.py
just/commands/linux.py
just/commands/tunnel.py
just/commands/view.py
just/commands/ext/__init__.py
just/commands/ext/add.py
just/commands/ext/edit.py
just/commands/ext/list.py
just/commands/ext/remove.py
just/core/__init__.py
just/core/config/__init__.py
just/core/config/config.py
just/core/config/utils.py
just/core/extension/__init__.py
just/core/extension/generator.py
just/core/extension/parser.py
just/core/extension/utils.py
just/core/extension/validator.py
just/core/installer/__init__.py
just/core/installer/binary.py
just/core/installer/decorator.py
just/core/installer/install_package.py
just/core/installer/package_info.py
just/core/installer/simple_release.py
just/core/installer/source/__init__.py
just/core/installer/source/base.py
just/core/installer/source/http.py
just/core/installer/source/local.py
just/core/system_probe/__init__.py
just/core/system_probe/system_info.py
just/core/system_probe/system_probe.py
just/installers/__init__.py
just/installers/claude-code/__init__.py
just/installers/claude-code/installer.py
just/installers/cloudflare/__init__.py
just/installers/cloudflare/installer.py
just/installers/docker/__init__.py
just/installers/docker/installer.py
just/installers/edit/__init__.py
just/installers/edit/installer.py
just/installers/mssh/__init__.py
just/installers/mssh/installer.py
just/installers/nvm/__init__.py
just/installers/nvm/installer.py
just/installers/qodercli/__init__.py
just/installers/qodercli/installer.py
just/installers/tailscale/__init__.py
just/installers/tailscale/installer.py
just/tui/__init__.py
just/tui/editor.py
just/tui/extension.py
just/tui/markdown.py
just/utils/__init__.py
just/utils/download_utils.py
just/utils/echo_utils.py
just/utils/env_utils.py
just/utils/file_utils.py
just/utils/format_utils.py
just/utils/progress.py
just/utils/shell_utils.py
just_cli-0.2.1.dist-info/METADATA
just_cli-0.2.1.dist-info/WHEEL
just_cli-0.2.1.dist-info/entry_points.txt
just_cli-0.2.1.dist-info/RECORD
