Metadata-Version: 2.4
Name: just-cli
Version: 0.2.1
Summary: Your all-in-one CLI Toolkit
Author-email: zzzcb <zjxs.zzzcb@gmail.com>
Requires-Python: >=3.10
Requires-Dist: httpx
Requires-Dist: prompt-toolkit>=3.0.0
Requires-Dist: py7zr
Requires-Dist: python-dotenv
Requires-Dist: rich>=14.2.0
Requires-Dist: textual>=6.4.0
Requires-Dist: typer>=0.20.0
Requires-Dist: zstandard
